sdl3-0.2.0rc0.dist-info/licenses/LICENSE
sdl3_alias/__init__.py
sdl3-0.2.0rc0.dist-info/METADATA
sdl3-0.2.0rc0.dist-info/WHEEL
sdl3-0.2.0rc0.dist-info/top_level.txt
sdl3-0.2.0rc0.dist-info/RECORD
